pandas_type_checks/__init__.py
pandas_type_checks/core.py
pandas_type_checks/decorator.py
pandas_type_checks/errors.py
pandas_type_checks/pandera_support.py
pandas_type_checks-1.1.3.dist-info/LICENSE
pandas_type_checks-1.1.3.dist-info/METADATA
pandas_type_checks-1.1.3.dist-info/WHEEL
pandas_type_checks-1.1.3.dist-info/top_level.txt
pandas_type_checks-1.1.3.dist-info/RECORD
