Metadata-Version: 2.1
Name: pandas-type-checks
Version: 1.1.3
Summary: Structural type checking for Pandas data frames.
Author-email: Martin Zuber <martin.zuber@sap.com>
License: BSD 3-Clause License
Project-URL: Source Code, https://github.com/mzuber/pandas-type-checks
Keywords: Pandas,type check
Platform: any
Classifier: Development Status :: 4 - Beta
Classifier: Intended Audience :: Developers
Classifier: License :: OSI Approved :: BSD License
Classifier: Operating System :: OS Independent
Classifier: Programming Language :: Python
Classifier: Programming Language :: Python :: 3
Classifier: Programming Language :: Python :: 3 :: Only
Classifier: Programming Language :: Python :: 3.8
Classifier: Programming Language :: Python :: 3.9
Classifier: Programming Language :: Python :: 3.10
Classifier: Programming Language :: Python :: 3.11
Classifier: Programming Language :: Python :: 3.12
Classifier: Topic :: Scientific/Engineering
Classifier: Topic :: Software Development :: Libraries
Classifier: Typing :: Typed
Requires-Python: >=3.8
License-File: LICENSE
Requires-Dist: pandas>=1.1.0
Provides-Extra: pandera
Requires-Dist: pandera>=0.20.3; extra == "pandera"
